alipay/__init__.py
alipay/exceptions.py
alipay/tests.py
alipay-0.7.1.dist-info/DESCRIPTION.rst
alipay-0.7.1.dist-info/METADATA
alipay-0.7.1.dist-info/metadata.json
alipay-0.7.1.dist-info/RECORD
alipay-0.7.1.dist-info/top_level.txt
alipay-0.7.1.dist-info/WHEEL
