Metadata-Version: 2.0
Name: alipay
Version: 0.7.1
Summary: An Unofficial Alipay API for Python
Home-page: https://github.com/lxneng/alipay
Author: Eric Lo
Author-email: lxneng@gmail.com
License: BSD
Platform: UNKNOWN
Requires-Dist: requests
Requires-Dist: six
Requires-Dist: pytz
